{"name":"Elkay LZS8WSLP","scoreData":{"2020-10-07":{"id":1251086038231825400,"name":"Elkay LZS8WSLP","score":5500,"level":2,"character":7,"platform":18,"runframes":5833,"runend":1021,"unknown1":4294966183,"unknown2":165,"rank":4331,"percentile":33.62967504598406},"2020-10-04":{"id":76561198001006180,"name":"Elkay LZS8WSLP","score":4000,"level":3,"character":4,"platform":18,"runframes":7001,"runend":1020,"unknown1":3568,"unknown2":200,"rank":5000,"percentile":33.45314164004259},"2020-10-03":{"id":8143921580964113000,"name":"Elkay LZS8WSLP","score":10400,"level":2,"character":4,"platform":18,"runframes":9547,"runend":1021,"unknown1":4294963200,"unknown2":146,"rank":4994,"percentile":36.781463661686495},"2020-10-01":{"id":3483834299772243000,"name":"Elkay LZS8WSLP","score":9700,"level":3,"character":0,"platform":18,"runframes":12492,"runend":1020,"unknown1":2438,"unknown2":3509,"rank":4120,"percentile":46.464777748895244}},"tenDayPercentiles":[],"tenDayDecayingPercentileScore":0,"scoresByDay":[],"rankSummary":{"mean":4611.25,"median":4331,"max":5000,"min":4120},"percentileSummary":{"mean":37.582264524152095,"median":33.62967504598406,"max":46.464777748895244,"min":33.45314164004259}}