{"name":"Felixavi","scoreData":{"2020-10-01":{"id":76561198272744540,"name":"Felixavi","score":2100,"level":1,"character":3,"platform":18,"runframes":2348,"runend":1022,"unknown1":2015,"unknown2":960,"rank":7228,"percentile":6.0696646737717685}},"tenDayPercentiles":[],"tenDayDecayingPercentileScore":0,"scoresByDay":[],"rankSummary":{"mean":7228,"median":7228,"max":7228,"min":7228},"percentileSummary":{"mean":6.0696646737717685,"median":6.0696646737717685,"max":6.0696646737717685,"min":6.0696646737717685}}