{"name":"FryGuy","scoreData":{"2020-09-29":{"id":76561198014524080,"name":"FryGuy","score":7800,"level":1,"character":3,"platform":18,"runframes":8535,"runend":1022,"unknown1":4294965403,"unknown2":107,"rank":5044,"percentile":9.817596566523605}},"tenDayPercentiles":[],"tenDayDecayingPercentileScore":0,"scoresByDay":[],"rankSummary":{"mean":5044,"median":5044,"max":5044,"min":5044},"percentileSummary":{"mean":9.817596566523605,"median":9.817596566523605,"max":9.817596566523605,"min":9.817596566523605}}