{"name":"Haugy","scoreData":{"2020-10-18":{"id":76561198947585140,"name":"Haugy","score":310025,"level":22,"character":6,"platform":18,"runframes":162651,"runend":1001,"unknown1":814,"unknown2":225,"rank":12,"percentile":99.8144399460189},"2020-10-17":{"id":76561198309925100,"name":"Haugy","score":114800,"level":10,"character":6,"platform":18,"runframes":64845,"runend":1013,"unknown1":1102,"unknown2":3421,"rank":273,"percentile":95.34883720930233},"2020-10-15":{"id":76561198058687300,"name":"Haugy","score":318875,"level":15,"character":6,"platform":18,"runframes":112174,"runend":1008,"unknown1":2124,"unknown2":4595,"rank":142,"percentile":97.55080771235018},"2020-10-07":{"id":76561197962166770,"name":"Haugy","score":29000,"level":3,"character":6,"platform":18,"runframes":20331,"runend":1020,"unknown1":4294966361,"unknown2":226,"rank":1713,"percentile":73.75843041079092},"2020-10-06":{"id":76561198064953600,"name":"Haugy","score":17300,"level":2,"character":6,"platform":18,"runframes":7677,"runend":1021,"unknown1":4294964722,"unknown2":4294964165,"rank":4368,"percentile":35.73215599705665},"2020-10-05":{"id":76561198038659420,"name":"Haugy","score":69550,"level":7,"character":6,"platform":18,"runframes":46348,"runend":1016,"unknown1":495,"unknown2":4294965098,"rank":784,"percentile":88.50557839107458},"2020-10-01":{"id":7392061125974166000,"name":"Haugy","score":97175,"level":7,"character":6,"platform":18,"runframes":58254,"runend":1016,"unknown1":4294966125,"unknown2":210,"rank":889,"percentile":88.4585391213933},"2020-09-30":{"id":2653380604114584000,"name":"Haugy","score":137250,"level":9,"character":6,"platform":18,"runframes":87270,"runend":1014,"unknown1":4294964816,"unknown2":877,"rank":170,"percentile":97.81201450025894},"2020-09-29":{"id":76561198072787150,"name":"Haugy","score":15800,"level":2,"character":8,"platform":18,"runframes":8624,"runend":1021,"unknown1":732,"unknown2":4294966524,"rank":3425,"percentile":38.76967095851216}},"tenDayPercentiles":[],"tenDayDecayingPercentileScore":0,"scoresByDay":[],"rankSummary":{"mean":1308.4444444444443,"median":784,"max":4368,"min":12},"percentileSummary":{"mean":79.52783047186199,"median":88.50557839107458,"max":99.8144399460189,"min":35.73215599705665}}