{"name":"HellSpeedrunner","scoreData":{"2020-10-20":{"id":76561197967795440,"name":"HellSpeedrunner","score":9050,"level":7,"character":8,"platform":18,"runframes":25302,"runend":1016,"unknown1":1732,"unknown2":4294967105,"rank":1653,"percentile":69.4074074074074},"2020-10-18":{"id":76561198004419760,"name":"HellSpeedrunner","score":32850,"level":8,"character":8,"platform":18,"runframes":33443,"runend":1015,"unknown1":4294962736,"unknown2":4294965002,"rank":1437,"percentile":75.77597840755735},"2020-10-17":{"id":738794387374097000,"name":"HellSpeedrunner","score":1300,"level":1,"character":8,"platform":18,"runframes":2904,"runend":1022,"unknown1":4294962561,"unknown2":30,"rank":5494,"percentile":6.07045143638851},"2020-10-14":{"id":76561197996643250,"name":"HellSpeedrunner","score":500,"level":1,"character":3,"platform":18,"runframes":620,"runend":1022,"unknown1":2180,"unknown2":4294967036,"rank":4920,"percentile":11.080983369486617},"2020-10-10":{"id":76561198362989800,"name":"HellSpeedrunner","score":6000,"level":2,"character":3,"platform":18,"runframes":3657,"runend":1021,"unknown1":3033,"unknown2":4294966754,"rank":4213,"percentile":36.14311704063069},"2020-10-08":{"id":76561198024987230,"name":"HellSpeedrunner","score":12075,"level":9,"character":3,"platform":18,"runframes":25932,"runend":1014,"unknown1":4294965979,"unknown2":649,"rank":355,"percentile":94.41552295314719},"2020-10-04":{"id":76561198416891070,"name":"HellSpeedrunner","score":2000,"level":3,"character":3,"platform":18,"runframes":5051,"runend":1020,"unknown1":4294964098,"unknown2":4294964808,"rank":5147,"percentile":31.496272630457938}},"tenDayPercentiles":[],"tenDayDecayingPercentileScore":0,"scoresByDay":[],"rankSummary":{"mean":3317,"median":4213,"max":5494,"min":355},"percentileSummary":{"mean":46.34139046358224,"median":36.14311704063069,"max":94.41552295314719,"min":6.07045143638851}}