{"name":"Xiaou","scoreData":{"2020-10-25":{"id":76561198160117660,"name":"Xiaou","score":8400,"level":4,"character":2,"platform":18,"runframes":7366,"runend":1019,"unknown1":4294963318,"unknown2":4294963447,"rank":2896,"percentile":47.83783783783784},"2020-10-07":{"id":76561198008316660,"name":"Xiaou","score":18100,"level":5,"character":2,"platform":18,"runframes":20534,"runend":1018,"unknown1":4294962910,"unknown2":4294962003,"rank":1163,"percentile":82.18884120171674}},"tenDayPercentiles":[],"tenDayDecayingPercentileScore":0,"scoresByDay":[],"rankSummary":{"mean":2029.5,"median":1163,"max":2896,"min":1163},"percentileSummary":{"mean":65.01333951977729,"median":47.83783783783784,"max":82.18884120171674,"min":47.83783783783784}}