{"name":"✪ NɪSu","scoreData":{"2020-10-21":{"id":76561198099213810,"name":"✪ NɪSu","score":1000,"level":1,"character":7,"platform":18,"runframes":2432,"runend":1022,"unknown1":4294967243,"unknown2":378,"rank":5201,"percentile":3.1296572280178765},"2020-09-29":{"id":76561198005575020,"name":"✪ NɪSu","score":8800,"level":1,"character":1,"platform":18,"runframes":1917,"runend":1022,"unknown1":1617,"unknown2":4294966397,"rank":4778,"percentile":14.574391988555078}},"tenDayDecayingPercentileMean":null,"rankSummary":{"mean":4989.5,"median":4778,"max":5201,"min":4778},"percentileSummary":{"mean":8.852024608286477,"median":3.1296572280178765,"max":14.574391988555078,"min":3.1296572280178765}}