{"name":"Nyarlythotep11","scoreData":{"2020-10-17":{"id":76561197968475470,"name":"Nyarlythotep11","score":29300,"level":4,"character":4,"platform":48,"runframes":20083,"runend":1019,"unknown1":4294966605,"unknown2":78,"rank":2416,"percentile":58.70383036935705}},"tenDayPercentiles":[],"tenDayDecayingPercentileScore":0,"scoresByDay":[],"rankSummary":{"mean":2416,"median":2416,"max":2416,"min":2416},"percentileSummary":{"mean":58.70383036935705,"median":58.70383036935705,"max":58.70383036935705,"min":58.70383036935705}}