{"name":"Mr.Domination","scoreData":{"2020-10-02":{"id":76561198391847700,"name":"Mr.Domination","score":4800,"level":3,"character":5,"platform":18,"runframes":12556,"runend":1020,"unknown1":4294965818,"unknown2":179,"rank":3703,"percentile":50.39528339809728},"2020-10-01":{"id":76561198000691700,"name":"Mr.Domination","score":10800,"level":3,"character":7,"platform":18,"runframes":17743,"runend":1020,"unknown1":4294961537,"unknown2":4294963666,"rank":4035,"percentile":47.56953470236548}},"tenDayPercentiles":[],"tenDayDecayingPercentileScore":0,"scoresByDay":[],"rankSummary":{"mean":3869,"median":3703,"max":4035,"min":3703},"percentileSummary":{"mean":48.98240905023138,"median":47.56953470236548,"max":50.39528339809728,"min":47.56953470236548}}