{"name":"OracleFish_666","scoreData":{"2020-09-29":{"id":76561198067562370,"name":"OracleFish_666","score":15500,"level":3,"character":0,"platform":48,"runframes":7729,"runend":1020,"unknown1":222,"unknown2":69,"rank":2949,"percentile":47.28183118741058}},"tenDayPercentiles":[],"tenDayDecayingPercentileScore":0,"scoresByDay":[],"rankSummary":{"mean":2949,"median":2949,"max":2949,"min":2949},"percentileSummary":{"mean":47.28183118741058,"median":47.28183118741058,"max":47.28183118741058,"min":47.28183118741058}}