{"name":"Owen Wilson","scoreData":{"2020-10-12":{"id":76561197995980720,"name":"Owen Wilson","score":19900,"level":4,"character":8,"platform":18,"runframes":14367,"runend":1019,"unknown1":4294965292,"unknown2":1446,"rank":1948,"percentile":67.46323529411765}},"tenDayPercentiles":[],"tenDayDecayingPercentileScore":0,"scoresByDay":[],"rankSummary":{"mean":1948,"median":1948,"max":1948,"min":1948},"percentileSummary":{"mean":67.46323529411765,"median":67.46323529411765,"max":67.46323529411765,"min":67.46323529411765}}