{"name":"imdacrunkest","scoreData":{"2020-11-02":{"id":76561198085938380,"name":"imdacrunkest","score":16300,"level":2,"character":10,"platform":48,"runframes":6743,"runend":1021,"unknown1":1923,"unknown2":2176,"rank":3221,"percentile":28.01251956181534},"2020-10-25":{"id":76561198027476480,"name":"imdacrunkest","score":500,"level":1,"character":4,"platform":48,"runframes":1315,"runend":1022,"unknown1":4294966486,"unknown2":554,"rank":5417,"percentile":2.4144144144144093}},"tenDayPercentiles":[],"tenDayDecayingPercentileScore":0,"scoresByDay":[],"rankSummary":{"mean":4319,"median":3221,"max":5417,"min":3221},"percentileSummary":{"mean":15.213466988114874,"median":2.4144144144144093,"max":28.01251956181534,"min":2.4144144144144093}}