{"name":"yourmum754","scoreData":{"2020-11-22":{"id":3391496276135399400,"name":"yourmum754","score":14700,"level":2,"character":3,"platform":48,"runframes":8101,"runend":1021,"unknown1":4294964067,"unknown2":4294964330,"rank":2621,"percentile":34.4836209052263}},"tenDayPercentiles":[],"tenDayDecayingPercentileScore":0,"scoresByDay":[],"rankSummary":{"mean":2621,"median":2621,"max":2621,"min":2621},"percentileSummary":{"mean":34.4836209052263,"median":34.4836209052263,"max":34.4836209052263,"min":34.4836209052263}}