{"name":"blackster55","scoreData":{"2020-10-04":{"id":76561198036674290,"name":"blackster55","score":7500,"level":4,"character":0,"platform":18,"runframes":6200,"runend":1019,"unknown1":4294967058,"unknown2":4294965459,"rank":3561,"percentile":52.609158679446224}},"tenDayPercentiles":[],"tenDayDecayingPercentileScore":0,"scoresByDay":[],"rankSummary":{"mean":3561,"median":3561,"max":3561,"min":3561},"percentileSummary":{"mean":52.609158679446224,"median":52.609158679446224,"max":52.609158679446224,"min":52.609158679446224}}