{"name":"bootysnat1chenod","scoreData":{"2020-11-08":{"id":76561197963193010,"name":"bootysnat1chenod","score":7850,"level":3,"character":3,"platform":48,"runframes":20903,"runend":1020,"unknown1":4294966393,"unknown2":6,"rank":2539,"percentile":46.171792152704136},"2020-10-13":{"id":76561198145928030,"name":"bootysnat1chenod","score":5100,"level":2,"character":3,"platform":48,"runframes":2490,"runend":1021,"unknown1":4294962946,"unknown2":308,"rank":4892,"percentile":16.6069906223359},"2020-10-11":{"id":6239910613751745000,"name":"bootysnat1chenod","score":4300,"level":2,"character":3,"platform":48,"runframes":2518,"runend":1021,"unknown1":4294966196,"unknown2":154,"rank":5220,"percentile":17.811023622047244},"2020-09-22":{"id":4609847584865940500,"name":"bootysnat1chenod","score":4000,"level":2,"character":3,"platform":48,"runframes":4483,"runend":1021,"unknown1":4294966942,"unknown2":78,"rank":1469,"percentile":40.373679935012184},"2020-09-21":{"id":8301456802388681000,"name":"bootysnat1chenod","score":4000,"level":2,"character":3,"platform":48,"runframes":4178,"runend":1021,"unknown1":394,"unknown2":4294965933,"rank":1880,"percentile":24.74969963956748},"2020-09-15":{"id":7708467989705667000,"name":"bootysnat1chenod","score":8800,"level":2,"character":0,"platform":48,"runframes":7155,"runend":1021,"unknown1":4294967219,"unknown2":4294965945,"rank":981,"percentile":46.035242290748904}},"tenDayPercentiles":[],"tenDayDecayingPercentileScore":0,"scoresByDay":[],"rankSummary":{"mean":2830.1666666666665,"median":1880,"max":5220,"min":981},"percentileSummary":{"mean":31.958071377069306,"median":24.74969963956748,"max":46.171792152704136,"min":16.6069906223359}}