{"name":"laser_machine","scoreData":{"2020-10-18":{"id":2824741878663046000,"name":"laser_machine","score":35200,"level":3,"character":3,"platform":48,"runframes":26402,"runend":1020,"unknown1":2349,"unknown2":4294966525,"rank":4177,"percentile":29.554655870445345}},"tenDayPercentiles":[],"tenDayDecayingPercentileScore":0,"scoresByDay":[],"rankSummary":{"mean":4177,"median":4177,"max":4177,"min":4177},"percentileSummary":{"mean":29.554655870445345,"median":29.554655870445345,"max":29.554655870445345,"min":29.554655870445345}}