{"name":"LMiranic","scoreData":{"2020-11-17":{"id":76561198030486530,"name":"LMiranic","score":57075,"level":5,"character":13,"platform":18,"runframes":42167,"runend":1018,"unknown1":4294966842,"unknown2":3087,"rank":879,"percentile":77.59060745278202},"2020-11-12":{"id":76561197989377040,"name":"LMiranic","score":19700,"level":2,"character":13,"platform":18,"runframes":12792,"runend":1021,"unknown1":34,"unknown2":67,"rank":1882,"percentile":55.886491557223266},"2020-11-02":{"id":9075859810793598000,"name":"LMiranic","score":90650,"level":12,"character":0,"platform":18,"runframes":73628,"runend":1011,"unknown1":548,"unknown2":2672,"rank":569,"percentile":87.3015873015873},"2020-10-27":{"id":76561198166024380,"name":"LMiranic","score":27700,"level":3,"character":13,"platform":18,"runframes":22114,"runend":1020,"unknown1":839,"unknown2":1443,"rank":2183,"percentile":56.15832831022705},"2020-10-26":{"id":6885073781049055000,"name":"LMiranic","score":39800,"level":9,"character":13,"platform":18,"runframes":82334,"runend":1014,"unknown1":2613,"unknown2":4294966108,"rank":554,"percentile":89.07114624505928},"2020-10-25":{"id":6405077966599565000,"name":"LMiranic","score":354750,"level":12,"character":9,"platform":18,"runframes":137812,"runend":1011,"unknown1":4294966300,"unknown2":4294964093,"rank":320,"percentile":94.25225225225225},"2020-10-24":{"id":6503550775901012000,"name":"LMiranic","score":52825,"level":6,"character":12,"platform":18,"runframes":44573,"runend":1017,"unknown1":868,"unknown2":2691,"rank":1231,"percentile":77.10349962769918},"2020-10-23":{"id":76561198351850560,"name":"LMiranic","score":10000,"level":1,"character":10,"platform":18,"runframes":4715,"runend":1022,"unknown1":1667,"unknown2":247,"rank":4751,"percentile":9.021260294962659},"2020-10-22":{"id":76561198088759340,"name":"LMiranic","score":257400,"level":18,"character":16,"platform":18,"runframes":166166,"runend":749,"unknown1":2847,"unknown2":853,"rank":64,"percentile":98.81288863764838},"2020-10-21":{"id":76561198003225940,"name":"LMiranic","score":36100,"level":4,"character":18,"platform":18,"runframes":32259,"runend":1019,"unknown1":3775,"unknown2":675,"rank":2107,"percentile":60.767511177347245},"2020-10-20":{"id":3595143993099818000,"name":"LMiranic","score":55875,"level":6,"character":14,"platform":18,"runframes":34911,"runend":1017,"unknown1":4294967047,"unknown2":2419,"rank":1700,"percentile":68.53703703703704},"2020-10-19":{"id":76561197970602110,"name":"LMiranic","score":36325,"level":8,"character":10,"platform":18,"runframes":48752,"runend":1015,"unknown1":63,"unknown2":508,"rank":608,"percentile":88.64996260284218},"2020-10-18":{"id":41627679000696504,"name":"LMiranic","score":57800,"level":5,"character":6,"platform":18,"runframes":37849,"runend":1018,"unknown1":4294964763,"unknown2":4294965414,"rank":2263,"percentile":61.84210526315789},"2020-10-17":{"id":8018332725655230000,"name":"LMiranic","score":35000,"level":4,"character":0,"platform":18,"runframes":22239,"runend":1019,"unknown1":4294962196,"unknown2":73,"rank":2288,"percentile":60.89261285909713},"2020-10-16":{"id":3796304193951898000,"name":"LMiranic","score":23600,"level":3,"character":6,"platform":18,"runframes":27779,"runend":1020,"unknown1":4496,"unknown2":4399,"rank":2009,"percentile":64.18762261458892},"2020-10-13":{"id":76561197981354320,"name":"LMiranic","score":18700,"level":2,"character":6,"platform":18,"runframes":13752,"runend":1021,"unknown1":3176,"unknown2":3070,"rank":3408,"percentile":41.909633418584825},"2020-10-12":{"id":76561197972342420,"name":"LMiranic","score":5100,"level":1,"character":6,"platform":18,"runframes":3881,"runend":1022,"unknown1":4296,"unknown2":6,"rank":5393,"percentile":9.893048128342244},"2020-10-11":{"id":76561197974414000,"name":"LMiranic","score":64850,"level":6,"character":6,"platform":18,"runframes":42301,"runend":1017,"unknown1":3683,"unknown2":4140,"rank":1153,"percentile":81.85826771653544},"2020-10-10":{"id":76561197963825950,"name":"LMiranic","score":45575,"level":5,"character":6,"platform":18,"runframes":38105,"runend":1018,"unknown1":4559,"unknown2":2885,"rank":647,"percentile":90.20618556701031},"2020-10-09":{"id":5259292481247032000,"name":"LMiranic","score":1500,"level":1,"character":6,"platform":18,"runframes":1021,"runend":1022,"unknown1":4294963559,"unknown2":4294965718,"rank":6236,"percentile":0.589923469387756},"2020-10-08":{"id":76561198084759340,"name":"LMiranic","score":31700,"level":3,"character":8,"platform":18,"runframes":21689,"runend":1020,"unknown1":891,"unknown2":889,"rank":2858,"percentile":54.9297996529421},"2020-10-07":{"id":76561198327747800,"name":"LMiranic","score":11400,"level":2,"character":6,"platform":18,"runframes":12740,"runend":1021,"unknown1":2424,"unknown2":42,"rank":3270,"percentile":49.892703862660944},"2020-10-06":{"id":7898720286494250000,"name":"LMiranic","score":14900,"level":2,"character":7,"platform":18,"runframes":10834,"runend":1021,"unknown1":4592,"unknown2":4819,"rank":4635,"percentile":31.8027961736571},"2020-10-04":{"id":3751747536969612300,"name":"LMiranic","score":19000,"level":3,"character":0,"platform":18,"runframes":16220,"runend":1020,"unknown1":5277,"unknown2":2750,"rank":3778,"percentile":49.72044728434505},"2020-10-03":{"id":76561197993381000,"name":"LMiranic","score":16200,"level":2,"character":3,"platform":18,"runframes":9923,"runend":1021,"unknown1":4294965762,"unknown2":370,"rank":3550,"percentile":55.06457330969866},"2020-10-02":{"id":76561198067562370,"name":"LMiranic","score":64200,"level":8,"character":0,"platform":18,"runframes":56597,"runend":1015,"unknown1":4294966120,"unknown2":1506,"rank":277,"percentile":96.3017553262763},"2020-10-01":{"id":76561197970274800,"name":"LMiranic","score":44950,"level":9,"character":0,"platform":18,"runframes":59106,"runend":1014,"unknown1":4294963404,"unknown2":4294965825,"rank":449,"percentile":94.17728099818041},"2020-09-30":{"id":76561198041628530,"name":"LMiranic","score":30600,"level":4,"character":0,"platform":18,"runframes":21080,"runend":1019,"unknown1":3462,"unknown2":79,"rank":1448,"percentile":81.26618332470223}},"tenDayPercentiles":[55.886491557223266,77.59060745278202],"tenDayDecayingPercentileScore":80.62085493040456,"scoresByDay":[24.05730209732646,56.563552833078106],"rankSummary":{"mean":2161.0714285714284,"median":1882,"max":6236,"min":64},"percentileSummary":{"mean":63.84598255235125,"median":61.84210526315789,"max":98.81288863764838,"min":0.589923469387756}}