{"name":"love_fan","scoreData":{"2020-10-03":{"id":76561197960517250,"name":"love_fan","score":100,"level":1,"character":3,"platform":18,"runframes":748,"runend":1022,"unknown1":1478,"unknown2":168,"rank":7843,"percentile":0.7090402633578066}},"tenDayPercentiles":[],"tenDayDecayingPercentileScore":0,"scoresByDay":[],"rankSummary":{"mean":7843,"median":7843,"max":7843,"min":7843},"percentileSummary":{"mean":0.7090402633578066,"median":0.7090402633578066,"max":0.7090402633578066,"min":0.7090402633578066}}