{"name":"lulfenborg","scoreData":{"2020-09-20":{"id":3469591594883362000,"name":"lulfenborg","score":12000,"level":3,"character":3,"platform":48,"runframes":8864,"runend":1020,"unknown1":4294966919,"unknown2":975,"rank":1280,"percentile":56.99394754539341},"2020-09-16":{"id":494312328818166000,"name":"lulfenborg","score":4100,"level":1,"character":2,"platform":48,"runframes":1978,"runend":1022,"unknown1":4294966029,"unknown2":10,"rank":2894,"percentile":6.254050550874922}},"tenDayPercentiles":[],"tenDayDecayingPercentileScore":0,"scoresByDay":[],"rankSummary":{"mean":2087,"median":1280,"max":2894,"min":1280},"percentileSummary":{"mean":31.623999048134166,"median":6.254050550874922,"max":56.99394754539341,"min":6.254050550874922}}