{"name":"JTinners95","scoreData":{"2020-10-19":{"id":7646429665275990000,"name":"JTinners95","score":6100,"level":2,"character":3,"platform":48,"runframes":5083,"runend":1021,"unknown1":4294964597,"unknown2":326,"rank":4439,"percentile":17.015706806282722}},"tenDayPercentiles":[],"tenDayDecayingPercentileScore":0,"scoresByDay":[],"rankSummary":{"mean":4439,"median":4439,"max":4439,"min":4439},"percentileSummary":{"mean":17.015706806282722,"median":17.015706806282722,"max":17.015706806282722,"min":17.015706806282722}}