{"name":"PiccadillyPro","scoreData":{"2020-09-15":{"id":7865341189679366000,"name":"PiccadillyPro","score":20650,"level":5,"character":1,"platform":48,"runframes":19797,"runend":1018,"unknown1":4294967077,"unknown2":13,"rank":346,"percentile":81.00220264317181}},"tenDayPercentiles":[],"tenDayDecayingPercentileScore":0,"scoresByDay":[],"rankSummary":{"mean":346,"median":346,"max":346,"min":346},"percentileSummary":{"mean":81.00220264317181,"median":81.00220264317181,"max":81.00220264317181,"min":81.00220264317181}}