{"name":"Plumbeck","scoreData":{"2020-09-16":{"id":6319687809528436000,"name":"Plumbeck","score":11700,"level":2,"character":0,"platform":48,"runframes":7107,"runend":1021,"unknown1":323,"unknown2":502,"rank":2096,"percentile":32.112767336357734}},"tenDayPercentiles":[],"tenDayDecayingPercentileScore":0,"scoresByDay":[],"rankSummary":{"mean":2096,"median":2096,"max":2096,"min":2096},"percentileSummary":{"mean":32.112767336357734,"median":32.112767336357734,"max":32.112767336357734,"min":32.112767336357734}}