{"name":"KhwanHan","scoreData":{"2020-09-17":{"id":5937861816905659000,"name":"KhwanHan","score":2500,"level":1,"character":3,"platform":48,"runframes":2222,"runend":1022,"unknown1":4294964814,"unknown2":4294964607,"rank":2598,"percentile":8.135833038556768}},"tenDayPercentiles":[],"tenDayDecayingPercentileScore":0,"scoresByDay":[],"rankSummary":{"mean":2598,"median":2598,"max":2598,"min":2598},"percentileSummary":{"mean":8.135833038556768,"median":8.135833038556768,"max":8.135833038556768,"min":8.135833038556768}}