{"name":"RiceCracker","scoreData":{"2020-10-21":{"id":76561199084996420,"name":"RiceCracker","score":0,"level":1,"character":2,"platform":18,"runframes":1897,"runend":1022,"unknown1":3041,"unknown2":71,"rank":5329,"percentile":0.7451564828614039}},"tenDayPercentiles":[],"tenDayDecayingPercentileScore":0,"scoresByDay":[],"rankSummary":{"mean":5329,"median":5329,"max":5329,"min":5329},"percentileSummary":{"mean":0.7451564828614039,"median":0.7451564828614039,"max":0.7451564828614039,"min":0.7451564828614039}}