{"name":"The Old Family Shame Man","scoreData":{"2020-10-16":{"id":76561198141265740,"name":"The Old Family Shame Man","score":11900,"level":4,"character":3,"platform":18,"runframes":27546,"runend":1019,"unknown1":4294965336,"unknown2":4294962563,"rank":1518,"percentile":72.94453361869093},"2020-10-15":{"id":76561198031826750,"name":"The Old Family Shame Man","score":12050,"level":6,"character":3,"platform":18,"runframes":26497,"runend":1017,"unknown1":2682,"unknown2":4294967193,"rank":1626,"percentile":71.77349313878756},"2020-10-02":{"id":76561197983019900,"name":"The Old Family Shame Man","score":32100,"level":5,"character":3,"platform":18,"runframes":25245,"runend":1018,"unknown1":4294965405,"unknown2":2043,"rank":972,"percentile":86.98914645584885},"2020-10-01":{"id":76561198072191020,"name":"The Old Family Shame Man","score":5700,"level":1,"character":3,"platform":18,"runframes":4352,"runend":1022,"unknown1":5271,"unknown2":124,"rank":5777,"percentile":24.928515726540155}},"tenDayPercentiles":[],"tenDayDecayingPercentileScore":0,"scoresByDay":[],"rankSummary":{"mean":2473.25,"median":1518,"max":5777,"min":972},"percentileSummary":{"mean":64.15892223496688,"median":71.77349313878756,"max":86.98914645584885,"min":24.928515726540155}}