{"name":"TheRisingOx","scoreData":{"2020-10-03":{"id":76561198018625890,"name":"TheRisingOx","score":1500,"level":1,"character":2,"platform":18,"runframes":638,"runend":1022,"unknown1":4294964212,"unknown2":857,"rank":7646,"percentile":3.203342618384397},"2020-10-01":{"id":7910986548280031000,"name":"TheRisingOx","score":28400,"level":4,"character":6,"platform":18,"runframes":22504,"runend":1019,"unknown1":499,"unknown2":150,"rank":2397,"percentile":68.85885105276839}},"tenDayPercentiles":[],"tenDayDecayingPercentileScore":0,"scoresByDay":[],"rankSummary":{"mean":5021.5,"median":2397,"max":7646,"min":2397},"percentileSummary":{"mean":36.03109683557639,"median":3.203342618384397,"max":68.85885105276839,"min":3.203342618384397}}