{"name":"Zealot13","scoreData":{"2020-09-26":{"id":3191806915874561000,"name":"Zealot13","score":1600,"level":1,"character":0,"platform":48,"runframes":2473,"runend":1022,"unknown1":117,"unknown2":33,"rank":2565,"percentile":1.1946050096339036}},"tenDayPercentiles":[],"tenDayDecayingPercentileScore":0,"scoresByDay":[],"rankSummary":{"mean":2565,"median":2565,"max":2565,"min":2565},"percentileSummary":{"mean":1.1946050096339036,"median":1.1946050096339036,"max":1.1946050096339036,"min":1.1946050096339036}}