{"name":"Siminski","scoreData":{"2020-11-01":{"id":76561198046804100,"name":"Siminski","score":18325,"level":8,"character":11,"platform":18,"runframes":35870,"runend":1015,"unknown1":4294964682,"unknown2":267,"rank":811,"percentile":82.78427205100957},"2020-10-23":{"id":7050159124605260000,"name":"Siminski","score":11300,"level":4,"character":16,"platform":18,"runframes":18404,"runend":1019,"unknown1":4294966570,"unknown2":4294966323,"rank":2952,"percentile":43.47826086956522},"2020-10-18":{"id":76561198069920430,"name":"Siminski","score":10600,"level":4,"character":19,"platform":18,"runframes":14466,"runend":1019,"unknown1":1035,"unknown2":2480,"rank":4058,"percentile":31.562078272604595},"2020-10-08":{"id":76561198011186530,"name":"Siminski","score":22075,"level":6,"character":7,"platform":18,"runframes":17400,"runend":1017,"unknown1":1234,"unknown2":400,"rank":1308,"percentile":79.38160593153495}},"tenDayPercentiles":[],"tenDayDecayingPercentileScore":0,"scoresByDay":[],"rankSummary":{"mean":2282.25,"median":1308,"max":4058,"min":811},"percentileSummary":{"mean":59.30155428117858,"median":43.47826086956522,"max":82.78427205100957,"min":31.562078272604595}}