{"name":"simmerdbeans","scoreData":{"2020-10-11":{"id":3471949047530084000,"name":"simmerdbeans","score":5800,"level":2,"character":3,"platform":48,"runframes":5166,"runend":1021,"unknown1":26,"unknown2":511,"rank":5115,"percentile":19.464566929133852},"2020-10-10":{"id":76561198128681390,"name":"simmerdbeans","score":500,"level":1,"character":3,"platform":48,"runframes":1779,"runend":1022,"unknown1":3823,"unknown2":130,"rank":6367,"percentile":3.486961795027284}},"tenDayPercentiles":[],"tenDayDecayingPercentileScore":0,"scoresByDay":[],"rankSummary":{"mean":5741,"median":5115,"max":6367,"min":5115},"percentileSummary":{"mean":11.475764362080568,"median":3.486961795027284,"max":19.464566929133852,"min":3.486961795027284}}