{"name":"Sire","scoreData":{"2020-10-07":{"id":76561197998392050,"name":"Sire","score":1500,"level":1,"character":3,"platform":18,"runframes":3705,"runend":1022,"unknown1":4294967273,"unknown2":451,"rank":6426,"percentile":1.5174739423666495}},"tenDayPercentiles":[],"tenDayDecayingPercentileScore":0,"scoresByDay":[],"rankSummary":{"mean":6426,"median":6426,"max":6426,"min":6426},"percentileSummary":{"mean":1.5174739423666495,"median":1.5174739423666495,"max":1.5174739423666495,"min":1.5174739423666495}}