{"name":"SoM‘s Yarny","scoreData":{"2020-11-20":{"id":7370502107108910000,"name":"SoM‘s Yarny","score":19225,"level":6,"character":7,"platform":18,"runframes":23776,"runend":1017,"unknown1":4294966891,"unknown2":2364,"rank":1593,"percentile":60.59405940594059},"2020-10-01":{"id":76561197990370320,"name":"SoM‘s Yarny","score":8000,"level":1,"character":3,"platform":18,"runframes":4892,"runend":1022,"unknown1":2917,"unknown2":96,"rank":5327,"percentile":30.777229009617884},"2020-09-30":{"id":76561198027920100,"name":"SoM‘s Yarny","score":11000,"level":3,"character":4,"platform":18,"runframes":14855,"runend":1020,"unknown1":4294963665,"unknown2":4294963117,"rank":3168,"percentile":58.99792853443812}},"tenDayPercentiles":[],"tenDayDecayingPercentileScore":0,"scoresByDay":[],"rankSummary":{"mean":3362.6666666666665,"median":3168,"max":5327,"min":1593},"percentileSummary":{"mean":50.123072316665535,"median":58.99792853443812,"max":60.59405940594059,"min":30.777229009617884}}