{"name":"suppadelicious","scoreData":{"2020-09-29":{"id":8563386921180055000,"name":"suppadelicious","score":27800,"level":3,"character":7,"platform":48,"runframes":19524,"runend":1020,"unknown1":126,"unknown2":2726,"rank":2599,"percentile":53.54077253218884},"2020-09-27":{"id":2594022089887507000,"name":"suppadelicious","score":29700,"level":4,"character":7,"platform":48,"runframes":28549,"runend":1019,"unknown1":4294965738,"unknown2":4294965347,"rank":840,"percentile":66.44}},"tenDayPercentiles":[],"tenDayDecayingPercentileScore":0,"scoresByDay":[],"rankSummary":{"mean":1719.5,"median":840,"max":2599,"min":840},"percentileSummary":{"mean":59.99038626609442,"median":53.54077253218884,"max":66.44,"min":53.54077253218884}}