{"name":"Swordfishbone","scoreData":{"2020-10-30":{"id":2551046817862686000,"name":"Swordfishbone","score":12800,"level":3,"character":0,"platform":18,"runframes":10752,"runend":1020,"unknown1":4294963083,"unknown2":282,"rank":1767,"percentile":62.813223836597174},"2020-10-17":{"id":76561197987903170,"name":"Swordfishbone","score":19600,"level":3,"character":0,"platform":18,"runframes":10376,"runend":1020,"unknown1":4294966325,"unknown2":4294964141,"rank":3060,"percentile":47.691518467852255},"2020-10-14":{"id":76561198799409360,"name":"Swordfishbone","score":5500,"level":2,"character":0,"platform":18,"runframes":4080,"runend":1021,"unknown1":4294963708,"unknown2":4294964323,"rank":3726,"percentile":32.664497469269705},"2020-10-12":{"id":76561198006440340,"name":"Swordfishbone","score":5800,"level":2,"character":0,"platform":18,"runframes":8410,"runend":1021,"unknown1":4294963402,"unknown2":50,"rank":4490,"percentile":24.983288770053477},"2020-10-09":{"id":76561198000130270,"name":"Swordfishbone","score":10800,"level":1,"character":0,"platform":18,"runframes":10605,"runend":1022,"unknown1":4294962914,"unknown2":810,"rank":5548,"percentile":11.559311224489804},"2020-10-08":{"id":76561198028287790,"name":"Swordfishbone","score":25700,"level":3,"character":0,"platform":18,"runframes":12533,"runend":1020,"unknown1":4294965530,"unknown2":4294962409,"rank":2982,"percentile":52.97365515065467},"2020-10-07":{"id":76561197990739060,"name":"Swordfishbone","score":11100,"level":1,"character":0,"platform":18,"runframes":8574,"runend":1022,"unknown1":197,"unknown2":218,"rank":5340,"percentile":18.163703249540163},"2020-10-06":{"id":76561198873752320,"name":"Swordfishbone","score":4200,"level":2,"character":0,"platform":18,"runframes":10505,"runend":1021,"unknown1":4294965681,"unknown2":4294965681,"rank":5803,"percentile":14.613686534216328},"2020-10-05":{"id":76561198275545460,"name":"Swordfishbone","score":1700,"level":1,"character":0,"platform":18,"runframes":1351,"runend":1022,"unknown1":4294962207,"unknown2":4294966445,"rank":6469,"percentile":5.049911920140929}},"tenDayPercentiles":[],"tenDayDecayingPercentileScore":0,"scoresByDay":[],"rankSummary":{"mean":4353.888888888889,"median":4490,"max":6469,"min":1767},"percentileSummary":{"mean":30.056977402534944,"median":24.983288770053477,"max":62.813223836597174,"min":5.049911920140929}}