{"name":"Gettin_Dumber","scoreData":{"2020-09-28":{"id":5000612036354177000,"name":"Gettin_Dumber","score":23600,"level":4,"character":3,"platform":48,"runframes":27538,"runend":1019,"unknown1":4294965930,"unknown2":50,"rank":1013,"percentile":53.1047265987025}},"tenDayPercentiles":[],"tenDayDecayingPercentileScore":0,"scoresByDay":[],"rankSummary":{"mean":1013,"median":1013,"max":1013,"min":1013},"percentileSummary":{"mean":53.1047265987025,"median":53.1047265987025,"max":53.1047265987025,"min":53.1047265987025}}