{"name":"GuppyTheCat","scoreData":{"2020-10-29":{"id":7600509988186647000,"name":"GuppyTheCat","score":16300,"level":2,"character":0,"platform":18,"runframes":10438,"runend":1021,"unknown1":4294965064,"unknown2":4294964934,"rank":3188,"percentile":33.36817896717541},"2020-10-23":{"id":76561197962054180,"name":"GuppyTheCat","score":25300,"level":4,"character":0,"platform":18,"runframes":24629,"runend":1019,"unknown1":4294964133,"unknown2":501,"rank":2675,"percentile":48.78375790078528},"2020-10-22":{"id":76561198010762110,"name":"GuppyTheCat","score":55550,"level":6,"character":0,"platform":18,"runframes":37320,"runend":1017,"unknown1":4294963042,"unknown2":4294965857,"rank":1189,"percentile":77.6144714527982},"2020-10-21":{"id":5736699424045114000,"name":"GuppyTheCat","score":3700,"level":2,"character":0,"platform":18,"runframes":3748,"runend":1021,"unknown1":4294964409,"unknown2":4294964947,"rank":4477,"percentile":16.61698956780924},"2020-10-20":{"id":8932083466154866000,"name":"GuppyTheCat","score":26875,"level":7,"character":0,"platform":18,"runframes":52008,"runend":1016,"unknown1":4294963874,"unknown2":4294963401,"rank":1501,"percentile":72.22222222222223}},"tenDayPercentiles":[],"tenDayDecayingPercentileScore":0,"scoresByDay":[],"rankSummary":{"mean":2606,"median":2675,"max":4477,"min":1189},"percentileSummary":{"mean":49.72112402215807,"median":48.78375790078528,"max":77.6144714527982,"min":16.61698956780924}}